LICENSE
MANIFEST.in
README.rst
setup.cfg
setup.py
names_translator/__init__.py
names_translator/name_utils.py
names_translator/names_translator.py
names_translator.egg-info/PKG-INFO
names_translator.egg-info/SOURCES.txt
names_translator.egg-info/dependency_links.txt
names_translator.egg-info/requires.txt
names_translator.egg-info/top_level.txt
names_translator/data/ua2ru.csv