Metadata-Version: 1.1
Name: names-translator
Version: 1.2.0
Summary: Automatic translation and transliteration of ukrainian names into Russian and English + some extra tools to deal with mixed languages, etc
Home-page: https://github.com/dchaplinsky/names-translator
Author: dchaplinsky
Author-email: chaplinsky.dmitry@gmail.com
License: MIT
Keywords: ukrainian names translation transliteration
Platform: UNKNOWN
Classifier: Development Status :: 5 - Production/Stable
Classifier: Intended Audience :: Developers
Classifier: License :: OSI Approved :: MIT License
Classifier: Programming Language :: Python :: 3
Classifier: Programming Language :: Python :: Implementation :: PyPy
Classifier: Programming Language :: Python :: 3.3
Classifier: Programming Language :: Python :: 3.4
Classifier: Programming Language :: Python :: 3.5
Classifier: Programming Language :: Python :: 3.6
Classifier: Natural Language :: Ukrainian
Classifier: Topic :: Text Processing :: Linguistic
Classifier: Topic :: Text Processing :: General
Classifier: Topic :: Text Processing :: Indexing
